aptbot/__init__.py
aptbot/args.py
aptbot/args_logic.py
aptbot/bot.py
aptbot/constants.py
aptbot/main.py
aptbot/resources/main.py
ttv_api/__init__.py
ttv_api/channel.py
ttv_api/emotes.py
ttv_api/stream.py
ttv_api/users.py
aptbot-0.2.1.dist-info/LICENSE
aptbot-0.2.1.dist-info/METADATA
aptbot-0.2.1.dist-info/WHEEL
aptbot-0.2.1.dist-info/entry_points.txt
aptbot-0.2.1.dist-info/top_level.txt
aptbot-0.2.1.dist-info/RECORD
