Metadata-Version: 2.1
Name: aptbot
Version: 0.2.1
Summary: A chatbot for twitch.tv
Home-page: https://github.com/atheridis/aptbot
Author: Georgios Atheridis
Author-email: atheridis@tutamail.com
Classifier: License :: OSI Approved :: MIT License
Classifier: Programming Language :: Python
Classifier: Programming Language :: Python :: 3.9
Requires-Python: >=3.7
License-File: LICENSE
Requires-Dist: python-dotenv
Requires-Dist: urllib3
